.gitignore
CHANGES.txt
CONTRIBUTORS.txt
COPYRIGHT.txt
LICENSE.txt
README.txt
setup.cfg
setup.py
tox.ini
docs/Makefile
docs/conf.py
docs/index.rst
pyramid_viewgroup/__init__.py
pyramid_viewgroup/group.py
pyramid_viewgroup/meta.zcml
pyramid_viewgroup/zcml.py
pyramid_viewgroup.egg-info/PKG-INFO
pyramid_viewgroup.egg-info/SOURCES.txt
pyramid_viewgroup.egg-info/dependency_links.txt
pyramid_viewgroup.egg-info/entry_points.txt
pyramid_viewgroup.egg-info/not-zip-safe
pyramid_viewgroup.egg-info/requires.txt
pyramid_viewgroup.egg-info/top_level.txt
pyramid_viewgroup/tests/__init__.py
pyramid_viewgroup/tests/test_all.py
pyramid_viewgroup/tests/fixtureapp/__init__.py
pyramid_viewgroup/tests/fixtureapp/another.zcml
pyramid_viewgroup/tests/fixtureapp/configure.zcml
pyramid_viewgroup/tests/fixtureapp/models.py
pyramid_viewgroup/tests/fixtureapp/views.py
pyramid_viewgroup/tests/fixtureapp/templates/fixture.pt