Metadata-Version: 1.0
Name: pyramid-viewgroup
Version: 0.5
Summary: An anlologue of Zope 3 "content providers" for Pyramid
Home-page: http://docs.pylonshq.com
Author: Chris McDonough, Agendaless Consulting
Author-email: pylons-discuss@googlegroups.com
License: BSD-derived (http://www.repoze.org/LICENSE.txt)
Keywords: web wsgi pyramid pylons zope3 content provider
Platform: UNKNOWN
Classifier: Intended Audience :: Developers
Classifier: Programming Language :: Python
Classifier: Framework :: Pylons
